setup.py
udacity_distributions_rashmi/Binomialdistribution.py
udacity_distributions_rashmi/Gaussiandistribution.py
udacity_distributions_rashmi/Generaldistribution.py
udacity_distributions_rashmi/__init__.py
udacity_distributions_rashmi.egg-info/PKG-INFO
udacity_distributions_rashmi.egg-info/SOURCES.txt
udacity_distributions_rashmi.egg-info/dependency_links.txt
udacity_distributions_rashmi.egg-info/not-zip-safe
udacity_distributions_rashmi.egg-info/top_level.txt